gans/datasets/__init__.py
gans/datasets/abstract_dataset.py
gans/datasets/cifar10.py
gans/datasets/dataset_factory.py
gans/datasets/fashion_mnist.py
gans/datasets/mnist.py
gans/datasets/problem_type.py
gans/datasets/summer2winter.py
gans/layers/__init__.py
gans/layers/advanced_layers.py
gans/layers/losses.py
gans/models/__init__.py
gans/models/custom_model.py
gans/models/model.py
gans/models/model_factories.py
gans/models/sequential.py
gans/trainers/__init__.py
gans/trainers/conditional_gan_trainer.py
gans/trainers/cycle_gan_trainer.py
gans/trainers/gan_checkpoint_manager.py
gans/trainers/gan_trainer.py
gans/trainers/vanilla_gan_trainer.py
gans/trainers/wasserstein_gan_trainer.py
gans/utils/__init__.py
gans/utils/config.py
gans/utils/constants.py
gans/utils/data_utils.py
gans/utils/logging.py
gans/utils/others.py
gans/utils/visualization.py
gans2-0.1.dist-info/DESCRIPTION.rst
gans2-0.1.dist-info/METADATA
gans2-0.1.dist-info/RECORD
gans2-0.1.dist-info/WHEEL
gans2-0.1.dist-info/metadata.json
gans2-0.1.dist-info/top_level.txt
gans2-0.1.dist-info/zip-safe
